pyhrp/__init__.py
pyhrp/algos.py
pyhrp/cluster.py
pyhrp/hrp.py
pyhrp/treelib.py
pyhrp-1.5.1.dist-info/METADATA
pyhrp-1.5.1.dist-info/WHEEL
pyhrp-1.5.1.dist-info/licenses/LICENSE
pyhrp-1.5.1.dist-info/RECORD
