Metadata-Version: 2.4
Name: pyhrp
Version: 1.5.1
Summary: Hierarchial risk parity
Project-URL: repository, https://github.com/tschm/pyhrp
Project-URL: homepage, https://tschm.github.io/pyhrp
Author-email: Thomas Schmelzer <thomas.schmelzer@gmail.com>
License-File: LICENSE
Requires-Python: >=3.12
Requires-Dist: numpy>=2
Requires-Dist: pandas>=2
Requires-Dist: scipy>=1.14.1
Provides-Extra: dev
Requires-Dist: marimo>=0.14.9; extra == 'dev'
Requires-Dist: matplotlib>=3.10.3; extra == 'dev'
Requires-Dist: polars==1.34.0; extra == 'dev'
Requires-Dist: pre-commit>=4.2.0; extra == 'dev'
Requires-Dist: pyarrow>=20.0.0; extra == 'dev'
Requires-Dist: pyportfolioopt>=1.5.6; extra == 'dev'
Requires-Dist: pytest-cov>=6.2.1; extra == 'dev'
Requires-Dist: pytest>=8.4.1; extra == 'dev'
Requires-Dist: security>=1.3.1; extra == 'dev'
